Metadata-Version: 1.0
Name: Pygiee
Version: 0.1
Summary: clinical trial information retriver
Home-page: UNKNOWN
Author: Leo
Author-email: UNKNOWN
License: MIT
Platform: UNKNOWN
